{
  "Condition": "LaboratoryNoOpponent",
  "DominantFoot": "Right",
  "FrameRateHz": 10,
  "NumberOfFrames": 43,
  "ContainsError": false,
  "Timestamps": [
    0.1,
    0.2,
    0.3,
    0.4,
    0.5,
    0.6,
    0.700000048,
    0.8000001,
    0.9000001,
    1.00000012,
    1.10000014,
    1.20000017,
    1.30000019,
    1.40000021,
    1.50000024,
    1.60000026,
    1.70000029,
    1.80000031,
    1.90000033,
    2.00000024,
    2.10000014,
    2.2,
    2.3,
    2.39999986,
    2.49999976,
    2.59999967,
    2.69999957,
    2.79999948,
    2.89999938,
    2.99999928,
    3.09999919,
    3.199999,
    3.299999,
    3.399999,
    3.49999881,
    3.59999871,
    3.69999862,
    3.79999852,
    3.89999843,
    3.99999833,
    4.09999847,
    4.19999838,
    4.29999828
  ],
  "TrialNumber": 4,
  "Duration": 4.29999828,
  "BallEvents": [
    {
      "Name": "Pass",
      "Timestamp": 2.3,
      "Position": {
        "x": -0.507275343,
        "y": 0.154739141,
        "z": -1.28517437
      }
    }
  ],
  "UserHeadPositions": [
    {
      "x": -2.361451,
      "y": 1.772456,
      "z": -0.010030508
    },
    {
      "x": -2.35968,
      "y": 1.77123237,
      "z": -0.0114269257
    },
    {
      "x": -2.35347152,
      "y": 1.770057,
      "z": -0.0110287666
    },
    {
      "x": -2.34081674,
      "y": 1.76661158,
      "z": -0.009971619
    },
    {
      "x": -2.3209188,
      "y": 1.76141477,
      "z": -0.00528907776
    },
    {
      "x": -2.29231524,
      "y": 1.75623894,
      "z": 0.004105091
    },
    {
      "x": -2.25290418,
      "y": 1.74911094,
      "z": 0.02123022
    },
    {
      "x": -2.19899249,
      "y": 1.733806,
      "z": 0.0417058468
    },
    {
      "x": -2.1308763,
      "y": 1.7024349,
      "z": 0.06413245
    },
    {
      "x": -2.055184,
      "y": 1.65198207,
      "z": 0.08354998
    },
    {
      "x": -1.96535778,
      "y": 1.6522994,
      "z": 0.08506322
    },
    {
      "x": -1.8587079,
      "y": 1.68857384,
      "z": 0.080685854
    },
    {
      "x": -1.72307491,
      "y": 1.6661787,
      "z": 0.112915993
    },
    {
      "x": -1.60979819,
      "y": 1.54909658,
      "z": 0.129181385
    },
    {
      "x": -1.50462961,
      "y": 1.464021,
      "z": 0.0963287354
    },
    {
      "x": -1.4188118,
      "y": 1.48838758,
      "z": -0.0127449036
    },
    {
      "x": -1.34451294,
      "y": 1.59500349,
      "z": -0.175047874
    },
    {
      "x": -1.28210425,
      "y": 1.64371586,
      "z": -0.3194077
    },
    {
      "x": -1.19320369,
      "y": 1.72150385,
      "z": -0.477432
    },
    {
      "x": -1.12022591,
      "y": 1.7474736,
      "z": -0.596236944
    },
    {
      "x": -1.05742431,
      "y": 1.68198919,
      "z": -0.7301669
    },
    {
      "x": -0.998456,
      "y": 1.59742785,
      "z": -0.8217423
    },
    {
      "x": -0.965490341,
      "y": 1.60680413,
      "z": -0.8983917
    },
    {
      "x": -0.943793535,
      "y": 1.63596225,
      "z": -0.9606252
    },
    {
      "x": -0.93670845,
      "y": 1.67467034,
      "z": -1.02140188
    },
    {
      "x": -0.92687726,
      "y": 1.70562148,
      "z": -1.07867551
    },
    {
      "x": -0.9238653,
      "y": 1.718322,
      "z": -1.15081024
    },
    {
      "x": -0.92247653,
      "y": 1.7147187,
      "z": -1.24253869
    },
    {
      "x": -0.9127271,
      "y": 1.72404778,
      "z": -1.32601476
    },
    {
      "x": -0.9002304,
      "y": 1.7113533,
      "z": -1.37312531
    },
    {
      "x": -0.8884351,
      "y": 1.66934538,
      "z": -1.4010303
    },
    {
      "x": -0.8837025,
      "y": 1.627928,
      "z": -1.41434288
    },
    {
      "x": -0.891034842,
      "y": 1.60528266,
      "z": -1.427783
    },
    {
      "x": -0.9064083,
      "y": 1.59995449,
      "z": -1.43171859
    },
    {
      "x": -0.937826157,
      "y": 1.60453415,
      "z": -1.41209483
    },
    {
      "x": -0.9796624,
      "y": 1.61197472,
      "z": -1.36936688
    },
    {
      "x": -1.05931783,
      "y": 1.61543274,
      "z": -1.28890491
    },
    {
      "x": -1.14748526,
      "y": 1.62602866,
      "z": -1.213557
    },
    {
      "x": -1.218718,
      "y": 1.66102362,
      "z": -1.15766287
    },
    {
      "x": -1.30047178,
      "y": 1.69026279,
      "z": -1.09580922
    },
    {
      "x": -1.37533188,
      "y": 1.6905756,
      "z": -1.03965211
    },
    {
      "x": -1.45209026,
      "y": 1.67095184,
      "z": -0.962155342
    },
    {
      "x": -1.54641843,
      "y": 1.641198,
      "z": -0.8721149
    }
  ],
  "UserDominantFootPositions": [
    {
      "x": -2.45968223,
      "y": 0.191607714,
      "z": -0.178833961
    },
    {
      "x": -2.45949531,
      "y": 0.191250682,
      "z": -0.179136515
    },
    {
      "x": -2.45960546,
      "y": 0.1913712,
      "z": -0.179088116
    },
    {
      "x": -2.458915,
      "y": 0.191973686,
      "z": -0.1812923
    },
    {
      "x": -2.45741343,
      "y": 0.191657782,
      "z": -0.180568218
    },
    {
      "x": -2.45526719,
      "y": 0.191178441,
      "z": -0.179888487
    },
    {
      "x": -2.45381427,
      "y": 0.189842463,
      "z": -0.177168846
    },
    {
      "x": -2.44332242,
      "y": 0.185272217,
      "z": -0.168203115
    },
    {
      "x": -2.38632464,
      "y": 0.212407947,
      "z": -0.137151718
    },
    {
      "x": -2.25029922,
      "y": 0.266533375,
      "z": -0.05084181
    },
    {
      "x": -2.075105,
      "y": 0.260559916,
      "z": -0.0249791145
    },
    {
      "x": -2.0853436,
      "y": 0.213637948,
      "z": -0.0606114864
    },
    {
      "x": -2.00787926,
      "y": 0.2609955,
      "z": -0.0306863785
    },
    {
      "x": -1.8516016,
      "y": 0.310186982,
      "z": 0.0827775
    },
    {
      "x": -1.670867,
      "y": 0.289275169,
      "z": 0.00313472748
    },
    {
      "x": -1.57594371,
      "y": 0.254304171,
      "z": -0.185391188
    },
    {
      "x": -1.55867839,
      "y": 0.197897553,
      "z": -0.323710442
    },
    {
      "x": -1.57520032,
      "y": 0.198443532,
      "z": -0.3344729
    },
    {
      "x": -1.590647,
      "y": 0.220197558,
      "z": -0.370706081
    },
    {
      "x": -1.60875583,
      "y": 0.3100145,
      "z": -0.501589537
    },
    {
      "x": -1.58278131,
      "y": 0.447414517,
      "z": -0.7992673
    },
    {
      "x": -1.27258873,
      "y": 0.329185367,
      "z": -1.16950774
    },
    {
      "x": -0.507275343,
      "y": 0.154739141,
      "z": -1.28517437
    },
    {
      "x": -0.3754263,
      "y": 0.433421969,
      "z": -1.11808515
    },
    {
      "x": -0.5126052,
      "y": 0.393121719,
      "z": -1.15321136
    },
    {
      "x": -0.789620638,
      "y": 0.320212841,
      "z": -1.32124519
    },
    {
      "x": -1.00493526,
      "y": 0.2622931,
      "z": -1.50868607
    },
    {
      "x": -1.10404682,
      "y": 0.171566963,
      "z": -1.5590322
    },
    {
      "x": -1.1098659,
      "y": 0.177560568,
      "z": -1.56698036
    },
    {
      "x": -1.11335349,
      "y": 0.1860733,
      "z": -1.5822103
    },
    {
      "x": -1.11841583,
      "y": 0.191462874,
      "z": -1.59720445
    },
    {
      "x": -1.129775,
      "y": 0.193106413,
      "z": -1.605505
    },
    {
      "x": -1.13451743,
      "y": 0.19567275,
      "z": -1.6083951
    },
    {
      "x": -1.13645649,
      "y": 0.194276452,
      "z": -1.60650826
    },
    {
      "x": -1.12936544,
      "y": 0.189806223,
      "z": -1.59283662
    },
    {
      "x": -1.12502146,
      "y": 0.189764023,
      "z": -1.58734488
    },
    {
      "x": -1.12206459,
      "y": 0.190148115,
      "z": -1.5787704
    },
    {
      "x": -1.119437,
      "y": 0.192205548,
      "z": -1.56717253
    },
    {
      "x": -1.09497166,
      "y": 0.222315788,
      "z": -1.545121
    },
    {
      "x": -1.09038806,
      "y": 0.338821769,
      "z": -1.45571709
    },
    {
      "x": -1.12725234,
      "y": 0.3858037,
      "z": -1.29168558
    },
    {
      "x": -1.23213339,
      "y": 0.394968033,
      "z": -1.11125731
    },
    {
      "x": -1.39979935,
      "y": 0.358852863,
      "z": -0.9273143
    }
  ],
  "UserNonDominantFootPositions": [
    {
      "x": -2.48135543,
      "y": 0.202010989,
      "z": 0.1392417
    },
    {
      "x": -2.48146939,
      "y": 0.201849461,
      "z": 0.1384139
    },
    {
      "x": -2.47997022,
      "y": 0.202654,
      "z": 0.1393733
    },
    {
      "x": -2.478173,
      "y": 0.200801969,
      "z": 0.13971138
    },
    {
      "x": -2.47596049,
      "y": 0.199852228,
      "z": 0.139173508
    },
    {
      "x": -2.47294068,
      "y": 0.198828936,
      "z": 0.138489485
    },
    {
      "x": -2.47204423,
      "y": 0.19741869,
      "z": 0.140300512
    },
    {
      "x": -2.47251821,
      "y": 0.19498086,
      "z": 0.143954277
    },
    {
      "x": -2.46507525,
      "y": 0.186652422,
      "z": 0.14409852
    },
    {
      "x": -2.44984555,
      "y": 0.173137426,
      "z": 0.149382591
    },
    {
      "x": -2.4448545,
      "y": 0.172669888,
      "z": 0.145878553
    },
    {
      "x": -2.329553,
      "y": 0.245576978,
      "z": 0.194225073
    },
    {
      "x": -2.032907,
      "y": 0.230885983,
      "z": 0.332639456
    },
    {
      "x": -1.79874992,
      "y": 0.181618452,
      "z": 0.406235456
    },
    {
      "x": -1.83955574,
      "y": 0.177969933,
      "z": 0.425061822
    },
    {
      "x": -1.85338449,
      "y": 0.182039261,
      "z": 0.418815136
    },
    {
      "x": -1.82676744,
      "y": 0.2276758,
      "z": 0.33795476
    },
    {
      "x": -1.77432084,
      "y": 0.2716124,
      "z": 0.132048845
    },
    {
      "x": -1.47369885,
      "y": 0.253003716,
      "z": -0.2060523
    },
    {
      "x": -1.16558051,
      "y": 0.230867386,
      "z": -0.539092541
    },
    {
      "x": -0.9095993,
      "y": 0.212055087,
      "z": -0.7764404
    },
    {
      "x": -0.8652611,
      "y": 0.161729574,
      "z": -0.8882165
    },
    {
      "x": -0.8832402,
      "y": 0.1535654,
      "z": -0.8702822
    },
    {
      "x": -0.88189435,
      "y": 0.174134731,
      "z": -0.8762324
    },
    {
      "x": -0.8791256,
      "y": 0.177336216,
      "z": -0.8617594
    },
    {
      "x": -0.8879378,
      "y": 0.182465792,
      "z": -0.8696778
    },
    {
      "x": -0.8978729,
      "y": 0.184026957,
      "z": -0.8776107
    },
    {
      "x": -0.9071636,
      "y": 0.1895585,
      "z": -0.8909421
    },
    {
      "x": -0.9323969,
      "y": 0.234114647,
      "z": -0.9565604
    },
    {
      "x": -1.08923316,
      "y": 0.284285784,
      "z": -1.15475965
    },
    {
      "x": -1.11351466,
      "y": 0.375032067,
      "z": -1.3362565
    },
    {
      "x": -1.088,
      "y": 0.370373726,
      "z": -1.41663718
    },
    {
      "x": -1.11664176,
      "y": 0.3422054,
      "z": -1.4341259
    },
    {
      "x": -1.172324,
      "y": 0.307962537,
      "z": -1.40109682
    },
    {
      "x": -1.26874781,
      "y": 0.269073129,
      "z": -1.35178041
    },
    {
      "x": -1.357518,
      "y": 0.238186717,
      "z": -1.2846067
    },
    {
      "x": -1.46549749,
      "y": 0.217512369,
      "z": -1.20620322
    },
    {
      "x": -1.519747,
      "y": 0.199760556,
      "z": -1.18876672
    },
    {
      "x": -1.54341078,
      "y": 0.196702242,
      "z": -1.1859374
    },
    {
      "x": -1.55906868,
      "y": 0.198337317,
      "z": -1.19422793
    },
    {
      "x": -1.56973672,
      "y": 0.197047472,
      "z": -1.19651389
    },
    {
      "x": -1.57736731,
      "y": 0.195378423,
      "z": -1.19747138
    },
    {
      "x": -1.58306408,
      "y": 0.192494392,
      "z": -1.19489455
    }
  ],
  "UserHipPositions": [
    {
      "x": -2.35930514,
      "y": 1.06881046,
      "z": 0.00407958031
    },
    {
      "x": -2.35808063,
      "y": 1.06817544,
      "z": 0.00196385384
    },
    {
      "x": -2.356262,
      "y": 1.06706178,
      "z": 0.00206160545
    },
    {
      "x": -2.35238433,
      "y": 1.06569934,
      "z": 0.00159096718
    },
    {
      "x": -2.34460759,
      "y": 1.06309474,
      "z": 0.00249409676
    },
    {
      "x": -2.3322947,
      "y": 1.05965579,
      "z": 0.009585381
    },
    {
      "x": -2.31423116,
      "y": 1.05387163,
      "z": 0.02573061
    },
    {
      "x": -2.29122853,
      "y": 1.04488683,
      "z": 0.0536949635
    },
    {
      "x": -2.27147031,
      "y": 1.023867,
      "z": 0.0705904961
    },
    {
      "x": -2.234001,
      "y": 0.9902272,
      "z": 0.08055377
    },
    {
      "x": -2.13884664,
      "y": 0.997995138,
      "z": 0.09127259
    },
    {
      "x": -2.02795959,
      "y": 1.034503,
      "z": 0.102977514
    },
    {
      "x": -1.96586132,
      "y": 1.02844739,
      "z": 0.09812927
    },
    {
      "x": -1.88927007,
      "y": 0.9107518,
      "z": 0.104233742
    },
    {
      "x": -1.81531239,
      "y": 0.8616986,
      "z": 0.07964778
    },
    {
      "x": -1.70631456,
      "y": 0.868525147,
      "z": -0.00170969963
    },
    {
      "x": -1.55430365,
      "y": 0.9473455,
      "z": -0.1743145
    },
    {
      "x": -1.437113,
      "y": 0.9843508,
      "z": -0.296345
    },
    {
      "x": -1.30206609,
      "y": 1.06442916,
      "z": -0.4685378
    },
    {
      "x": -1.19957685,
      "y": 1.09524691,
      "z": -0.579748154
    },
    {
      "x": -1.07688379,
      "y": 1.006909,
      "z": -0.6900494
    },
    {
      "x": -0.9875493,
      "y": 0.9125993,
      "z": -0.799598
    },
    {
      "x": -0.9737184,
      "y": 0.9503248,
      "z": -0.9165318
    },
    {
      "x": -0.9784186,
      "y": 1.02201545,
      "z": -1.00636387
    },
    {
      "x": -0.9050076,
      "y": 1.01670945,
      "z": -1.03933334
    },
    {
      "x": -0.901981831,
      "y": 1.06392431,
      "z": -1.09663653
    },
    {
      "x": -0.8943901,
      "y": 1.04723561,
      "z": -1.1603415
    },
    {
      "x": -0.9149966,
      "y": 1.01486325,
      "z": -1.24322653
    },
    {
      "x": -0.9722996,
      "y": 1.03027928,
      "z": -1.318749
    },
    {
      "x": -1.01333857,
      "y": 1.035307,
      "z": -1.35652757
    },
    {
      "x": -1.06017089,
      "y": 1.03535843,
      "z": -1.38793969
    },
    {
      "x": -1.08798122,
      "y": 1.03341365,
      "z": -1.41584969
    },
    {
      "x": -1.10417938,
      "y": 1.03447533,
      "z": -1.43070984
    },
    {
      "x": -1.10518718,
      "y": 1.04097629,
      "z": -1.43481183
    },
    {
      "x": -1.11044264,
      "y": 1.04268,
      "z": -1.41557169
    },
    {
      "x": -1.12811112,
      "y": 1.04751837,
      "z": -1.39268589
    },
    {
      "x": -1.17175317,
      "y": 1.04787183,
      "z": -1.34314394
    },
    {
      "x": -1.25037575,
      "y": 1.0430876,
      "z": -1.27530456
    },
    {
      "x": -1.33950567,
      "y": 1.05491316,
      "z": -1.21427894
    },
    {
      "x": -1.41899014,
      "y": 1.07011592,
      "z": -1.15853643
    },
    {
      "x": -1.50503039,
      "y": 1.06031048,
      "z": -1.11186862
    },
    {
      "x": -1.570519,
      "y": 1.05375826,
      "z": -1.06930041
    },
    {
      "x": -1.64964533,
      "y": 1.04314137,
      "z": -1.01168084
    }
  ],
  "OpponentHipPositions": []
}