{
  "Condition": "LaboratoryInteractive",
  "DominantFoot": "Right",
  "FrameRateHz": 10,
  "NumberOfFrames": 61,
  "ContainsError": false,
  "Timestamps": [
    0.1,
    0.2,
    0.3,
    0.4,
    0.5,
    0.6,
    0.700000048,
    0.8000001,
    0.9000001,
    1.00000012,
    1.10000014,
    1.20000017,
    1.30000019,
    1.40000021,
    1.50000024,
    1.60000026,
    1.70000029,
    1.80000031,
    1.90000033,
    2.00000024,
    2.10000014,
    2.2,
    2.3,
    2.39999986,
    2.49999976,
    2.59999967,
    2.69999957,
    2.79999948,
    2.89999938,
    2.99999928,
    3.09999919,
    3.199999,
    3.299999,
    3.399999,
    3.49999881,
    3.59999871,
    3.69999862,
    3.79999852,
    3.89999843,
    3.99999833,
    4.09999847,
    4.19999838,
    4.29999828,
    4.399998,
    4.499998,
    4.599998,
    4.699998,
    4.799998,
    4.89999771,
    4.99999762,
    5.09999752,
    5.19999743,
    5.29999733,
    5.399997,
    5.499997,
    5.599997,
    5.699997,
    5.799997,
    5.89999676,
    5.99999666,
    6.09999657
  ],
  "TrialNumber": 9,
  "Duration": 6.09999657,
  "BallEvents": [
    {
      "Name": "Pass",
      "Timestamp": 3.49999881,
      "Position": {
        "x": -0.889855,
        "y": 0.38981986,
        "z": -1.17274857
      }
    },
    {
      "Name": "Intercepted",
      "Timestamp": 5.799997,
      "Position": {
        "x": 10.2685318,
        "y": 0.0,
        "z": -0.40565744
      }
    }
  ],
  "UserHeadPositions": [
    {
      "x": -2.269247,
      "y": 1.93820071,
      "z": -0.004130602
    },
    {
      "x": -2.26587582,
      "y": 1.935545,
      "z": -0.00360512733
    },
    {
      "x": -2.26129532,
      "y": 1.93189025,
      "z": -0.002623558
    },
    {
      "x": -2.25586271,
      "y": 1.92710161,
      "z": -0.00125384331
    },
    {
      "x": -2.24676561,
      "y": 1.91898656,
      "z": 0.0017812252
    },
    {
      "x": -2.23301554,
      "y": 1.90497613,
      "z": 0.008559465
    },
    {
      "x": -2.21506882,
      "y": 1.8813324,
      "z": 0.0209670067
    },
    {
      "x": -2.19986582,
      "y": 1.862384,
      "z": 0.0323185921
    },
    {
      "x": -2.185151,
      "y": 1.8508445,
      "z": 0.0468204021
    },
    {
      "x": -2.17756939,
      "y": 1.84805822,
      "z": 0.0587360859
    },
    {
      "x": -2.16884947,
      "y": 1.84668648,
      "z": 0.073745966
    },
    {
      "x": -2.16100168,
      "y": 1.84394252,
      "z": 0.08574748
    },
    {
      "x": -2.15250349,
      "y": 1.83472276,
      "z": 0.09414959
    },
    {
      "x": -2.13683558,
      "y": 1.831025,
      "z": 0.106934071
    },
    {
      "x": -2.11385918,
      "y": 1.82430661,
      "z": 0.131721735
    },
    {
      "x": -2.07653475,
      "y": 1.81643736,
      "z": 0.184762955
    },
    {
      "x": -2.04055357,
      "y": 1.80818868,
      "z": 0.243098259
    },
    {
      "x": -1.990229,
      "y": 1.8027252,
      "z": 0.305165529
    },
    {
      "x": -1.92661226,
      "y": 1.8186326,
      "z": 0.354341865
    },
    {
      "x": -1.87347925,
      "y": 1.806288,
      "z": 0.396140337
    },
    {
      "x": -1.799378,
      "y": 1.76118183,
      "z": 0.45161283
    },
    {
      "x": -1.69643509,
      "y": 1.7513144,
      "z": 0.5260507
    },
    {
      "x": -1.60017717,
      "y": 1.67396283,
      "z": 0.595879436
    },
    {
      "x": -1.49672043,
      "y": 1.57470059,
      "z": 0.6520158
    },
    {
      "x": -1.45218432,
      "y": 1.53863382,
      "z": 0.6623266
    },
    {
      "x": -1.41320646,
      "y": 1.53384376,
      "z": 0.5950575
    },
    {
      "x": -1.391291,
      "y": 1.58903027,
      "z": 0.476734757
    },
    {
      "x": -1.37108648,
      "y": 1.70265627,
      "z": 0.306208253
    },
    {
      "x": -1.35301554,
      "y": 1.755358,
      "z": 0.134094477
    },
    {
      "x": -1.29436719,
      "y": 1.76556063,
      "z": -0.07383323
    },
    {
      "x": -1.21874774,
      "y": 1.86253893,
      "z": -0.232867479
    },
    {
      "x": -1.19474185,
      "y": 1.87575614,
      "z": -0.388847351
    },
    {
      "x": -1.19695365,
      "y": 1.8046298,
      "z": -0.5243962
    },
    {
      "x": -1.14508784,
      "y": 1.84784484,
      "z": -0.653557539
    },
    {
      "x": -1.07393515,
      "y": 1.92707956,
      "z": -0.83245635
    },
    {
      "x": -1.03310359,
      "y": 1.92761743,
      "z": -0.9958899
    },
    {
      "x": -1.007933,
      "y": 1.87253022,
      "z": -1.12947965
    },
    {
      "x": -0.96091187,
      "y": 1.80781114,
      "z": -1.26411939
    },
    {
      "x": -0.899534345,
      "y": 1.81331277,
      "z": -1.409889
    },
    {
      "x": -0.851439834,
      "y": 1.88579071,
      "z": -1.48445082
    },
    {
      "x": -0.823338151,
      "y": 1.92499042,
      "z": -1.53618288
    },
    {
      "x": -0.806794763,
      "y": 1.92537546,
      "z": -1.5863688
    },
    {
      "x": -0.7901684,
      "y": 1.91954875,
      "z": -1.65266061
    },
    {
      "x": -0.7801081,
      "y": 1.90759087,
      "z": -1.72671485
    },
    {
      "x": -0.7730366,
      "y": 1.9085598,
      "z": -1.7642529
    },
    {
      "x": -0.7523817,
      "y": 1.91245294,
      "z": -1.78590035
    },
    {
      "x": -0.7264167,
      "y": 1.91596055,
      "z": -1.80891967
    },
    {
      "x": -0.6804298,
      "y": 1.91403294,
      "z": -1.842057
    },
    {
      "x": -0.615085959,
      "y": 1.9060657,
      "z": -1.882828
    },
    {
      "x": -0.5507194,
      "y": 1.90142369,
      "z": -1.91208911
    },
    {
      "x": -0.4552859,
      "y": 1.90617275,
      "z": -1.94335723
    },
    {
      "x": -0.354629159,
      "y": 1.91675687,
      "z": -1.97244811
    },
    {
      "x": -0.270645022,
      "y": 1.92775583,
      "z": -2.00045371
    },
    {
      "x": -0.176560044,
      "y": 1.92664027,
      "z": -2.03640485
    },
    {
      "x": -0.100085855,
      "y": 1.91339922,
      "z": -2.06498933
    },
    {
      "x": 0.02181518,
      "y": 1.88218153,
      "z": -2.11275268
    },
    {
      "x": 0.13727355,
      "y": 1.86630106,
      "z": -2.15287137
    },
    {
      "x": 0.2519797,
      "y": 1.88208258,
      "z": -2.159969
    },
    {
      "x": 0.35563612,
      "y": 1.89538729,
      "z": -2.12833762
    },
    {
      "x": 0.4548328,
      "y": 1.881985,
      "z": -2.089546
    },
    {
      "x": 0.545043349,
      "y": 1.84875107,
      "z": -2.047602
    }
  ],
  "UserDominantFootPositions": [
    {
      "x": -2.43300533,
      "y": 0.2796768,
      "z": -0.09500623
    },
    {
      "x": -2.43323565,
      "y": 0.279790878,
      "z": -0.09497523
    },
    {
      "x": -2.433126,
      "y": 0.279683828,
      "z": -0.09477806
    },
    {
      "x": -2.43327618,
      "y": 0.279679656,
      "z": -0.09467363
    },
    {
      "x": -2.43334341,
      "y": 0.2797557,
      "z": -0.0945799351
    },
    {
      "x": -2.43371058,
      "y": 0.279793859,
      "z": -0.0940794945
    },
    {
      "x": -2.43486261,
      "y": 0.2803769,
      "z": -0.093568325
    },
    {
      "x": -2.43478441,
      "y": 0.28023088,
      "z": -0.09275031
    },
    {
      "x": -2.43397331,
      "y": 0.280053377,
      "z": -0.09140682
    },
    {
      "x": -2.43136454,
      "y": 0.2799486,
      "z": -0.08987546
    },
    {
      "x": -2.42440128,
      "y": 0.28416276,
      "z": -0.08774614
    },
    {
      "x": -2.42913818,
      "y": 0.285738,
      "z": -0.0612950325
    },
    {
      "x": -2.44080639,
      "y": 0.2736925,
      "z": -0.06122136
    },
    {
      "x": -2.4382453,
      "y": 0.274167061,
      "z": -0.0608458519
    },
    {
      "x": -2.43737841,
      "y": 0.274487257,
      "z": -0.0608472824
    },
    {
      "x": -2.434523,
      "y": 0.2736777,
      "z": -0.0541937351
    },
    {
      "x": -2.42661572,
      "y": 0.272560835,
      "z": -0.04873848
    },
    {
      "x": -2.37452364,
      "y": 0.288196921,
      "z": -0.0211868286
    },
    {
      "x": -2.284801,
      "y": 0.2997862,
      "z": 0.121165276
    },
    {
      "x": -2.24333429,
      "y": 0.277439475,
      "z": 0.206281424
    },
    {
      "x": -2.26640129,
      "y": 0.268764138,
      "z": 0.172563314
    },
    {
      "x": -2.21705341,
      "y": 0.3009466,
      "z": 0.215538979
    },
    {
      "x": -2.077201,
      "y": 0.332069874,
      "z": 0.391855836
    },
    {
      "x": -1.82468522,
      "y": 0.3184762,
      "z": 0.6763319
    },
    {
      "x": -1.64144218,
      "y": 0.3442086,
      "z": 0.7465229
    },
    {
      "x": -1.568765,
      "y": 0.343921542,
      "z": 0.5628569
    },
    {
      "x": -1.568376,
      "y": 0.3647436,
      "z": 0.362601519
    },
    {
      "x": -1.62385833,
      "y": 0.353915572,
      "z": 0.277995
    },
    {
      "x": -1.70103633,
      "y": 0.2525493,
      "z": 0.298910856
    },
    {
      "x": -1.71253622,
      "y": 0.257440925,
      "z": 0.296871543
    },
    {
      "x": -1.742613,
      "y": 0.3577646,
      "z": 0.1961062
    },
    {
      "x": -1.83815229,
      "y": 0.48282814,
      "z": 0.08719325
    },
    {
      "x": -1.7924,
      "y": 0.572345,
      "z": -0.3136692
    },
    {
      "x": -1.48534,
      "y": 0.391667843,
      "z": -0.8043158
    },
    {
      "x": -0.889855,
      "y": 0.38981986,
      "z": -1.17274857
    },
    {
      "x": -0.875039935,
      "y": 0.4969406,
      "z": -1.30811715
    },
    {
      "x": -0.916124,
      "y": 0.3476696,
      "z": -1.39495063
    },
    {
      "x": -0.9849483,
      "y": 0.2710532,
      "z": -1.49171638
    },
    {
      "x": -0.938372254,
      "y": 0.265753865,
      "z": -1.51963687
    },
    {
      "x": -0.9198066,
      "y": 0.2908429,
      "z": -1.51614356
    },
    {
      "x": -0.9226271,
      "y": 0.294629574,
      "z": -1.5088253
    },
    {
      "x": -0.9226874,
      "y": 0.287400961,
      "z": -1.504462
    },
    {
      "x": -0.921164155,
      "y": 0.287109971,
      "z": -1.51347876
    },
    {
      "x": -0.9244803,
      "y": 0.28824842,
      "z": -1.51772165
    },
    {
      "x": -0.9298798,
      "y": 0.287600517,
      "z": -1.51683712
    },
    {
      "x": -0.9322618,
      "y": 0.2890694,
      "z": -1.51914787
    },
    {
      "x": -0.93241775,
      "y": 0.291322,
      "z": -1.52263737
    },
    {
      "x": -0.923288941,
      "y": 0.2911526,
      "z": -1.52886581
    },
    {
      "x": -0.9133779,
      "y": 0.2925707,
      "z": -1.53818464
    },
    {
      "x": -0.903217435,
      "y": 0.299711823,
      "z": -1.558224
    },
    {
      "x": -0.8809837,
      "y": 0.3309362,
      "z": -1.644145
    },
    {
      "x": -0.7399274,
      "y": 0.403939724,
      "z": -1.80511212
    },
    {
      "x": -0.5551177,
      "y": 0.4010042,
      "z": -1.98136163
    },
    {
      "x": -0.2933184,
      "y": 0.3419876,
      "z": -2.160446
    },
    {
      "x": -0.0855672359,
      "y": 0.318953753,
      "z": -2.24767041
    },
    {
      "x": 0.06391406,
      "y": 0.3143158,
      "z": -2.26249
    },
    {
      "x": 0.0976510048,
      "y": 0.304258585,
      "z": -2.27107024
    },
    {
      "x": 0.109074354,
      "y": 0.294000626,
      "z": -2.25254464
    },
    {
      "x": 0.1137017,
      "y": 0.3009796,
      "z": -2.2456
    },
    {
      "x": 0.123358727,
      "y": 0.304843426,
      "z": -2.24266076
    },
    {
      "x": 0.130649567,
      "y": 0.3022778,
      "z": -2.239247
    }
  ],
  "UserNonDominantFootPositions": [
    {
      "x": -2.37634039,
      "y": 0.266924739,
      "z": 0.156679392
    },
    {
      "x": -2.37666845,
      "y": 0.266831279,
      "z": 0.156702757
    },
    {
      "x": -2.376841,
      "y": 0.267042637,
      "z": 0.156748533
    },
    {
      "x": -2.377232,
      "y": 0.266986,
      "z": 0.156971216
    },
    {
      "x": -2.37717247,
      "y": 0.2671218,
      "z": 0.15692687
    },
    {
      "x": -2.37645,
      "y": 0.266463876,
      "z": 0.157165051
    },
    {
      "x": -2.374498,
      "y": 0.266801119,
      "z": 0.158577681
    },
    {
      "x": -2.37479353,
      "y": 0.265941858,
      "z": 0.159560919
    },
    {
      "x": -2.37351942,
      "y": 0.265127182,
      "z": 0.160171509
    },
    {
      "x": -2.37303638,
      "y": 0.2644025,
      "z": 0.16053009
    },
    {
      "x": -2.374496,
      "y": 0.264299273,
      "z": 0.163985014
    },
    {
      "x": -2.37176132,
      "y": 0.26279223,
      "z": 0.16314292
    },
    {
      "x": -2.36901283,
      "y": 0.2628467,
      "z": 0.162895441
    },
    {
      "x": -2.36577034,
      "y": 0.26565516,
      "z": 0.176558733
    },
    {
      "x": -2.36186647,
      "y": 0.266334176,
      "z": 0.219691277
    },
    {
      "x": -2.353104,
      "y": 0.2649995,
      "z": 0.293766856
    },
    {
      "x": -2.3535037,
      "y": 0.2488501,
      "z": 0.325225472
    },
    {
      "x": -2.35110331,
      "y": 0.246030688,
      "z": 0.329546928
    },
    {
      "x": -2.34425879,
      "y": 0.25914526,
      "z": 0.344696283
    },
    {
      "x": -2.23495626,
      "y": 0.352744818,
      "z": 0.477493882
    },
    {
      "x": -2.062028,
      "y": 0.371016264,
      "z": 0.715271354
    },
    {
      "x": -1.86325061,
      "y": 0.2976768,
      "z": 0.9295708
    },
    {
      "x": -1.85047114,
      "y": 0.229733109,
      "z": 0.977482557
    },
    {
      "x": -1.78978765,
      "y": 0.245698929,
      "z": 0.967568159
    },
    {
      "x": -1.772123,
      "y": 0.250111461,
      "z": 0.9782201
    },
    {
      "x": -1.80190408,
      "y": 0.228764772,
      "z": 0.964120865
    },
    {
      "x": -1.80269992,
      "y": 0.2275337,
      "z": 0.952631831
    },
    {
      "x": -1.78785908,
      "y": 0.2737409,
      "z": 0.9245584
    },
    {
      "x": -1.69009888,
      "y": 0.337028265,
      "z": 0.804632664
    },
    {
      "x": -1.58828151,
      "y": 0.387059927,
      "z": 0.4001758
    },
    {
      "x": -1.44724619,
      "y": 0.35464406,
      "z": -0.0135843754
    },
    {
      "x": -1.33848059,
      "y": 0.325369239,
      "z": -0.379678249
    },
    {
      "x": -1.37854922,
      "y": 0.2239418,
      "z": -0.4527874
    },
    {
      "x": -1.37241447,
      "y": 0.240305424,
      "z": -0.449970722
    },
    {
      "x": -1.31303084,
      "y": 0.329254031,
      "z": -0.5367167
    },
    {
      "x": -1.15703571,
      "y": 0.289101124,
      "z": -0.7861798
    },
    {
      "x": -0.9810246,
      "y": 0.255946279,
      "z": -0.9431226
    },
    {
      "x": -1.02412665,
      "y": 0.256875634,
      "z": -0.9188323
    },
    {
      "x": -0.9161614,
      "y": 0.368587852,
      "z": -1.09182143
    },
    {
      "x": -0.8417505,
      "y": 0.355702639,
      "z": -1.271203
    },
    {
      "x": -0.781782031,
      "y": 0.305913448,
      "z": -1.45025826
    },
    {
      "x": -0.746817231,
      "y": 0.293097734,
      "z": -1.57489634
    },
    {
      "x": -0.7577692,
      "y": 0.27887857,
      "z": -1.59732032
    },
    {
      "x": -0.7476131,
      "y": 0.282225132,
      "z": -1.59808826
    },
    {
      "x": -0.7419809,
      "y": 0.284761071,
      "z": -1.60839534
    },
    {
      "x": -0.709310651,
      "y": 0.29863596,
      "z": -1.63541889
    },
    {
      "x": -0.650682569,
      "y": 0.3029499,
      "z": -1.6874733
    },
    {
      "x": -0.573074,
      "y": 0.3028226,
      "z": -1.7783463
    },
    {
      "x": -0.5194136,
      "y": 0.299324036,
      "z": -1.8704102
    },
    {
      "x": -0.527932763,
      "y": 0.280652881,
      "z": -1.91081738
    },
    {
      "x": -0.514941335,
      "y": 0.269973636,
      "z": -1.91857171
    },
    {
      "x": -0.508610368,
      "y": 0.267413378,
      "z": -1.91256928
    },
    {
      "x": -0.506796241,
      "y": 0.270323277,
      "z": -1.91024756
    },
    {
      "x": -0.5010704,
      "y": 0.272470117,
      "z": -1.91088748
    },
    {
      "x": -0.48921144,
      "y": 0.271355033,
      "z": -1.91751361
    },
    {
      "x": -0.448614717,
      "y": 0.281443954,
      "z": -1.93256783
    },
    {
      "x": -0.301881433,
      "y": 0.324965239,
      "z": -1.96063256
    },
    {
      "x": -0.0743171,
      "y": 0.391296148,
      "z": -2.0156014
    },
    {
      "x": 0.190852165,
      "y": 0.371415138,
      "z": -2.044285
    },
    {
      "x": 0.499038577,
      "y": 0.321998239,
      "z": -1.99345231
    },
    {
      "x": 0.753298759,
      "y": 0.322946429,
      "z": -1.8976891
    }
  ],
  "UserHipPositions": [
    {
      "x": -2.30397654,
      "y": 1.2065587,
      "z": 2.76565552E-05
    },
    {
      "x": -2.304412,
      "y": 1.20517862,
      "z": 0.00144386292
    },
    {
      "x": -2.305049,
      "y": 1.2039026,
      "z": 0.00251436234
    },
    {
      "x": -2.306126,
      "y": 1.20262015,
      "z": 0.004158497
    },
    {
      "x": -2.30727816,
      "y": 1.20157182,
      "z": 0.00559067726
    },
    {
      "x": -2.30931664,
      "y": 1.19995594,
      "z": 0.009650946
    },
    {
      "x": -2.311421,
      "y": 1.19791949,
      "z": 0.0154592991
    },
    {
      "x": -2.31425428,
      "y": 1.19547772,
      "z": 0.0243659019
    },
    {
      "x": -2.31604242,
      "y": 1.19253385,
      "z": 0.03673315
    },
    {
      "x": -2.3172636,
      "y": 1.18929315,
      "z": 0.0493042469
    },
    {
      "x": -2.31834269,
      "y": 1.18641675,
      "z": 0.0583503246
    },
    {
      "x": -2.31926966,
      "y": 1.18198192,
      "z": 0.06584287
    },
    {
      "x": -2.31807375,
      "y": 1.17830145,
      "z": 0.0754318237
    },
    {
      "x": -2.31463528,
      "y": 1.16886544,
      "z": 0.07614398
    },
    {
      "x": -2.2984252,
      "y": 1.16400254,
      "z": 0.09903073
    },
    {
      "x": -2.26610518,
      "y": 1.15764475,
      "z": 0.13274765
    },
    {
      "x": -2.226028,
      "y": 1.14364028,
      "z": 0.195073843
    },
    {
      "x": -2.190948,
      "y": 1.12915719,
      "z": 0.264612079
    },
    {
      "x": -2.13135481,
      "y": 1.159163,
      "z": 0.31918323
    },
    {
      "x": -2.08725739,
      "y": 1.15861869,
      "z": 0.3799032
    },
    {
      "x": -2.027029,
      "y": 1.09596992,
      "z": 0.453718066
    },
    {
      "x": -1.93832481,
      "y": 1.13691974,
      "z": 0.560429931
    },
    {
      "x": -1.89146483,
      "y": 1.03616512,
      "z": 0.594416738
    },
    {
      "x": -1.87417853,
      "y": 1.0040226,
      "z": 0.6254833
    },
    {
      "x": -1.85242784,
      "y": 0.9666492,
      "z": 0.6227977
    },
    {
      "x": -1.79867208,
      "y": 0.958379149,
      "z": 0.606533647
    },
    {
      "x": -1.734619,
      "y": 0.995732069,
      "z": 0.515996337
    },
    {
      "x": -1.6485635,
      "y": 1.066114,
      "z": 0.354913831
    },
    {
      "x": -1.58635628,
      "y": 1.10454166,
      "z": 0.1909256
    },
    {
      "x": -1.56331742,
      "y": 1.07955492,
      "z": 0.0230691433
    },
    {
      "x": -1.45232642,
      "y": 1.19576573,
      "z": -0.158974409
    },
    {
      "x": -1.34039772,
      "y": 1.20148647,
      "z": -0.3314891
    },
    {
      "x": -1.27050889,
      "y": 1.07644677,
      "z": -0.5041702
    },
    {
      "x": -1.22883046,
      "y": 1.17878222,
      "z": -0.6518028
    },
    {
      "x": -1.17122877,
      "y": 1.27922356,
      "z": -0.8229346
    },
    {
      "x": -1.11235654,
      "y": 1.24835086,
      "z": -0.974138
    },
    {
      "x": -1.02714574,
      "y": 1.15394139,
      "z": -1.11866927
    },
    {
      "x": -1.005438,
      "y": 1.088991,
      "z": -1.32915235
    },
    {
      "x": -0.9543468,
      "y": 1.11519241,
      "z": -1.39238238
    },
    {
      "x": -0.9313475,
      "y": 1.1802547,
      "z": -1.47423029
    },
    {
      "x": -0.909787059,
      "y": 1.21388173,
      "z": -1.53477311
    },
    {
      "x": -0.892762065,
      "y": 1.20680022,
      "z": -1.5985837
    },
    {
      "x": -0.879467368,
      "y": 1.20423353,
      "z": -1.65086937
    },
    {
      "x": -0.8643342,
      "y": 1.20929956,
      "z": -1.68857312
    },
    {
      "x": -0.849215865,
      "y": 1.200281,
      "z": -1.7228055
    },
    {
      "x": -0.828775764,
      "y": 1.19984543,
      "z": -1.7550571
    },
    {
      "x": -0.79192245,
      "y": 1.19831085,
      "z": -1.79033971
    },
    {
      "x": -0.746876836,
      "y": 1.18882418,
      "z": -1.81766486
    },
    {
      "x": -0.681873441,
      "y": 1.17503262,
      "z": -1.85300231
    },
    {
      "x": -0.606921554,
      "y": 1.16705608,
      "z": -1.89857459
    },
    {
      "x": -0.5106193,
      "y": 1.17273378,
      "z": -1.942128
    },
    {
      "x": -0.426767945,
      "y": 1.17947638,
      "z": -1.986223
    },
    {
      "x": -0.3341292,
      "y": 1.19833791,
      "z": -2.014125
    },
    {
      "x": -0.248679757,
      "y": 1.19288993,
      "z": -2.05032086
    },
    {
      "x": -0.162067056,
      "y": 1.17581272,
      "z": -2.08297849
    },
    {
      "x": -0.0363104343,
      "y": 1.1619817,
      "z": -2.14279342
    },
    {
      "x": 0.0814394951,
      "y": 1.160797,
      "z": -2.1709125
    },
    {
      "x": 0.186858773,
      "y": 1.17662716,
      "z": -2.16114879
    },
    {
      "x": 0.2825966,
      "y": 1.20073831,
      "z": -2.14702821
    },
    {
      "x": 0.376987457,
      "y": 1.19223309,
      "z": -2.14024234
    },
    {
      "x": 0.4741187,
      "y": 1.16338336,
      "z": -2.122513
    }
  ],
  "OpponentHipPositions": [
    {
      "x": 4.0,
      "y": 0.0,
      "z": 0.0
    },
    {
      "x": 4.0,
      "y": 0.0,
      "z": 0.0
    },
    {
      "x": 4.0,
      "y": 0.0,
      "z": 0.0
    },
    {
      "x": 4.0,
      "y": 0.0,
      "z": 0.0
    },
    {
      "x": 4.0,
      "y": 0.0,
      "z": 0.0
    },
    {
      "x": 4.0,
      "y": 0.0,
      "z": 0.0
    },
    {
      "x": 4.0,
      "y": 0.0,
      "z": 0.0
    },
    {
      "x": 4.0,
      "y": 0.0,
      "z": 0.0
    },
    {
      "x": 4.0,
      "y": 0.0,
      "z": 0.0
    },
    {
      "x": 4.0,
      "y": 0.0,
      "z": 0.0
    },
    {
      "x": 4.0,
      "y": 0.0,
      "z": 0.0
    },
    {
      "x": 4.0,
      "y": 0.0,
      "z": 0.0
    },
    {
      "x": 4.0,
      "y": 0.0,
      "z": 0.0
    },
    {
      "x": 4.0,
      "y": 0.0,
      "z": 0.0
    },
    {
      "x": 4.0,
      "y": 0.0,
      "z": 0.0
    },
    {
      "x": 4.0,
      "y": 0.0,
      "z": 0.0
    },
    {
      "x": 4.0,
      "y": 0.0,
      "z": 0.0
    },
    {
      "x": 3.998128,
      "y": 0.0,
      "z": 0.0001957907
    },
    {
      "x": 3.958299,
      "y": 0.0,
      "z": 0.004361178
    },
    {
      "x": 3.88010144,
      "y": 0.0,
      "z": 0.0125392554
    },
    {
      "x": 3.7440238,
      "y": 0.0,
      "z": 0.0267705955
    },
    {
      "x": 3.5599184,
      "y": 0.0,
      "z": 0.0460900553
    },
    {
      "x": 3.32532454,
      "y": 0.0,
      "z": 0.075341
    },
    {
      "x": 3.04604435,
      "y": 0.0,
      "z": 0.128195211
    },
    {
      "x": 2.77172279,
      "y": 0.0,
      "z": 0.207437053
    },
    {
      "x": 2.4307375,
      "y": 0.0,
      "z": 0.352560639
    },
    {
      "x": 2.17318678,
      "y": 0.0,
      "z": 0.487866759
    },
    {
      "x": 1.96179676,
      "y": 0.0,
      "z": 0.6078113
    },
    {
      "x": 1.81257927,
      "y": 0.0,
      "z": 0.6948504
    },
    {
      "x": 1.675533,
      "y": 0.0,
      "z": 0.7764628
    },
    {
      "x": 1.59600079,
      "y": 0.0,
      "z": 0.819093466
    },
    {
      "x": 1.548969,
      "y": 0.0,
      "z": 0.8241555
    },
    {
      "x": 1.52688,
      "y": 0.0,
      "z": 0.78491807
    },
    {
      "x": 1.526004,
      "y": 0.0,
      "z": 0.699975133
    },
    {
      "x": 1.5446651,
      "y": 0.0,
      "z": 0.5689004
    },
    {
      "x": 1.58005667,
      "y": 0.0,
      "z": 0.3897946
    },
    {
      "x": 1.64104617,
      "y": 0.0,
      "z": 0.167473674
    },
    {
      "x": 1.74887443,
      "y": 0.0,
      "z": -0.0581893921
    },
    {
      "x": 1.9050827,
      "y": 0.0,
      "z": -0.272301555
    },
    {
      "x": 2.10587335,
      "y": 0.0,
      "z": -0.462982327
    },
    {
      "x": 2.32519364,
      "y": 0.0,
      "z": -0.6136412
    },
    {
      "x": 2.573366,
      "y": 0.0,
      "z": -0.739534736
    },
    {
      "x": 2.9317975,
      "y": 0.0,
      "z": -0.8653535
    },
    {
      "x": 3.29367447,
      "y": 0.0,
      "z": -0.945110857
    },
    {
      "x": 3.69650483,
      "y": 0.0,
      "z": -0.991693735
    },
    {
      "x": 4.13232374,
      "y": 0.0,
      "z": -1.00338769
    },
    {
      "x": 4.60445738,
      "y": 0.0,
      "z": -0.9787099
    },
    {
      "x": 5.104355,
      "y": 0.0,
      "z": -0.9264085
    },
    {
      "x": 5.60266447,
      "y": 0.0,
      "z": -0.8739572
    },
    {
      "x": 6.050106,
      "y": 0.0,
      "z": -0.827031434
    },
    {
      "x": 6.54909563,
      "y": 0.0,
      "z": -0.774937153
    },
    {
      "x": 7.1029253,
      "y": 0.0,
      "z": -0.7181516
    },
    {
      "x": 7.604025,
      "y": 0.0,
      "z": -0.6678601
    },
    {
      "x": 8.102641,
      "y": 0.0,
      "z": -0.6184756
    },
    {
      "x": 8.550128,
      "y": 0.0,
      "z": -0.5744072
    },
    {
      "x": 9.104053,
      "y": 0.0,
      "z": -0.5199547
    },
    {
      "x": 9.60699,
      "y": 0.0,
      "z": -0.470534056
    },
    {
      "x": 10.0902348,
      "y": 0.0,
      "z": -0.423134744
    },
    {
      "x": 10.53032,
      "y": 0.0,
      "z": -0.380334944
    },
    {
      "x": 10.9162855,
      "y": 0.0,
      "z": -0.344304174
    },
    {
      "x": 11.2231188,
      "y": 0.0,
      "z": -0.316973925
    }
  ]
}