{
  "Condition": "InSitu",
  "DominantFoot": "Right",
  "FrameRateHz": 10,
  "NumberOfFrames": 70,
  "ContainsError": false,
  "Timestamps": [
    0.1,
    0.2,
    0.3,
    0.4,
    0.5,
    0.6,
    0.700000048,
    0.8000001,
    0.9000001,
    1.00000012,
    1.10000014,
    1.20000017,
    1.30000019,
    1.40000021,
    1.50000024,
    1.60000026,
    1.70000029,
    1.80000031,
    1.90000033,
    2.00000024,
    2.10000014,
    2.2,
    2.3,
    2.39999986,
    2.49999976,
    2.59999967,
    2.69999957,
    2.79999948,
    2.89999938,
    2.99999928,
    3.09999919,
    3.199999,
    3.299999,
    3.399999,
    3.49999881,
    3.59999871,
    3.69999862,
    3.79999852,
    3.89999843,
    3.99999833,
    4.09999847,
    4.19999838,
    4.29999828,
    4.399998,
    4.499998,
    4.599998,
    4.699998,
    4.799998,
    4.89999771,
    4.99999762,
    5.09999752,
    5.19999743,
    5.29999733,
    5.399997,
    5.499997,
    5.599997,
    5.699997,
    5.799997,
    5.89999676,
    5.99999666,
    6.09999657,
    6.19999647,
    6.29999638,
    6.39999628,
    6.499996,
    6.599996,
    6.699996,
    6.799996,
    6.899996,
    6.99999571
  ],
  "TrialNumber": 4,
  "Duration": 6.99999571,
  "BallEvents": [],
  "UserHeadPositions": [
    {
      "x": -3.41855621,
      "y": 1.74360061,
      "z": -0.419353962
    },
    {
      "x": -3.42587,
      "y": 1.73985434,
      "z": -0.428565741
    },
    {
      "x": -3.42564,
      "y": 1.73700881,
      "z": -0.4264431
    },
    {
      "x": -3.40986633,
      "y": 1.74032223,
      "z": -0.406719923
    },
    {
      "x": -3.39387226,
      "y": 1.74059665,
      "z": -0.3903861
    },
    {
      "x": -3.37506771,
      "y": 1.73995316,
      "z": -0.3771963
    },
    {
      "x": -3.34234047,
      "y": 1.74009645,
      "z": -0.3575728
    },
    {
      "x": -3.30617523,
      "y": 1.73658037,
      "z": -0.352211475
    },
    {
      "x": -3.262082,
      "y": 1.73379874,
      "z": -0.358659744
    },
    {
      "x": -3.19631481,
      "y": 1.72809863,
      "z": -0.364063263
    },
    {
      "x": -3.11893463,
      "y": 1.728176,
      "z": -0.379391432
    },
    {
      "x": -3.0211997,
      "y": 1.7324127,
      "z": -0.385918379
    },
    {
      "x": -2.92339039,
      "y": 1.74395239,
      "z": -0.3970468
    },
    {
      "x": -2.81440115,
      "y": 1.76761591,
      "z": -0.383501768
    },
    {
      "x": -2.715468,
      "y": 1.72513545,
      "z": -0.3798883
    },
    {
      "x": -2.62802267,
      "y": 1.66541171,
      "z": -0.353909254
    },
    {
      "x": -2.553358,
      "y": 1.7319597,
      "z": -0.31150198
    },
    {
      "x": -2.42688,
      "y": 1.78752065,
      "z": -0.221215248
    },
    {
      "x": -2.29172087,
      "y": 1.745408,
      "z": -0.144746542
    },
    {
      "x": -2.122963,
      "y": 1.685311,
      "z": -0.0538654327
    },
    {
      "x": -1.94092083,
      "y": 1.722869,
      "z": 0.0487120152
    },
    {
      "x": -1.76756907,
      "y": 1.738806,
      "z": 0.1301043
    },
    {
      "x": -1.62309551,
      "y": 1.7383734,
      "z": 0.20013833
    },
    {
      "x": -1.48354721,
      "y": 1.69541049,
      "z": 0.255229235
    },
    {
      "x": -1.30585384,
      "y": 1.61959076,
      "z": 0.3140397
    },
    {
      "x": -1.10396338,
      "y": 1.57640278,
      "z": 0.398437977
    },
    {
      "x": -0.9036188,
      "y": 1.59205,
      "z": 0.492242575
    },
    {
      "x": -0.7372937,
      "y": 1.58245754,
      "z": 0.5379939
    },
    {
      "x": -0.5919018,
      "y": 1.61226392,
      "z": 0.540843
    },
    {
      "x": -0.4281311,
      "y": 1.6766119,
      "z": 0.503938437
    },
    {
      "x": -0.2800169,
      "y": 1.648762,
      "z": 0.5164144
    },
    {
      "x": -0.1139617,
      "y": 1.57952762,
      "z": 0.5370579
    },
    {
      "x": 0.0284395218,
      "y": 1.63579524,
      "z": 0.5100672
    },
    {
      "x": 0.190556049,
      "y": 1.69536626,
      "z": 0.4488833
    },
    {
      "x": 0.275355339,
      "y": 1.72043717,
      "z": 0.412395
    },
    {
      "x": 0.473020554,
      "y": 1.81189632,
      "z": 0.309030771
    },
    {
      "x": 0.581222057,
      "y": 1.90070975,
      "z": 0.235395908
    },
    {
      "x": 0.66892767,
      "y": 1.9865613,
      "z": 0.189196348
    },
    {
      "x": 0.716313839,
      "y": 1.4971143,
      "z": -0.398787975
    },
    {
      "x": 0.7986584,
      "y": 1.5245266,
      "z": -0.14445281
    },
    {
      "x": 0.8710909,
      "y": 1.55416048,
      "z": -0.16408205
    },
    {
      "x": 0.8864598,
      "y": 1.55418432,
      "z": -0.09851885
    },
    {
      "x": 0.750756264,
      "y": 1.61958659,
      "z": -0.03797531
    },
    {
      "x": 0.6725426,
      "y": 1.64632428,
      "z": -0.0271015167
    },
    {
      "x": 0.5862322,
      "y": 1.67470181,
      "z": -0.039958
    },
    {
      "x": 0.488156319,
      "y": 1.70436668,
      "z": -0.07925892
    },
    {
      "x": 0.382097721,
      "y": 1.70751035,
      "z": -0.137326
    },
    {
      "x": 0.274782181,
      "y": 1.69407833,
      "z": -0.20771122
    },
    {
      "x": 0.172180176,
      "y": 1.6950649,
      "z": -0.2776289
    },
    {
      "x": 0.0652265549,
      "y": 1.72653461,
      "z": -0.3330016
    },
    {
      "x": -0.05446863,
      "y": 1.75071812,
      "z": -0.370028973
    },
    {
      "x": -0.177577019,
      "y": 1.74736214,
      "z": -0.3920114
    },
    {
      "x": -0.298902035,
      "y": 1.73388767,
      "z": -0.401371956
    },
    {
      "x": -0.425907135,
      "y": 1.72116351,
      "z": -0.393139124
    },
    {
      "x": -0.544518948,
      "y": 1.73606741,
      "z": -0.373296261
    },
    {
      "x": -0.6747184,
      "y": 1.7611481,
      "z": -0.368149281
    },
    {
      "x": -0.8100171,
      "y": 1.75420392,
      "z": -0.3720405
    },
    {
      "x": -0.940963268,
      "y": 1.72873461,
      "z": -0.3851347
    },
    {
      "x": -1.06129742,
      "y": 1.69792151,
      "z": -0.402200222
    },
    {
      "x": -1.162919,
      "y": 1.69623888,
      "z": -0.4251685
    },
    {
      "x": -1.269795,
      "y": 1.727442,
      "z": -0.43696475
    },
    {
      "x": -1.38670921,
      "y": 1.75573075,
      "z": -0.439522266
    },
    {
      "x": -1.49782133,
      "y": 1.7626406,
      "z": -0.432368279
    },
    {
      "x": -1.59782219,
      "y": 1.7534802,
      "z": -0.415036917
    },
    {
      "x": -1.71328545,
      "y": 1.73772311,
      "z": -0.3832116
    },
    {
      "x": -1.82018328,
      "y": 1.71896219,
      "z": -0.337770939
    },
    {
      "x": -1.91859245,
      "y": 1.72967291,
      "z": -0.2931564
    },
    {
      "x": -2.02325058,
      "y": 1.7434541,
      "z": -0.282664776
    },
    {
      "x": -2.12576962,
      "y": 1.73532856,
      "z": -0.28361702
    },
    {
      "x": -2.22799349,
      "y": 1.72273839,
      "z": -0.304256439
    }
  ],
  "UserDominantFootPositions": [
    {
      "x": -3.55613327,
      "y": 0.233299851,
      "z": -0.397991419
    },
    {
      "x": -3.54811859,
      "y": 0.23277843,
      "z": -0.399190664
    },
    {
      "x": -3.547884,
      "y": 0.231079459,
      "z": -0.39759016
    },
    {
      "x": -3.5460062,
      "y": 0.229452133,
      "z": -0.395735264
    },
    {
      "x": -3.54416275,
      "y": 0.227218747,
      "z": -0.3936169
    },
    {
      "x": -3.54301357,
      "y": 0.228056312,
      "z": -0.389397383
    },
    {
      "x": -3.539237,
      "y": 0.2278204,
      "z": -0.389769554
    },
    {
      "x": -3.53182316,
      "y": 0.229481936,
      "z": -0.39434433
    },
    {
      "x": -3.52782631,
      "y": 0.225056887,
      "z": -0.390913
    },
    {
      "x": -3.515811,
      "y": 0.22378242,
      "z": -0.38931036
    },
    {
      "x": -3.49798,
      "y": 0.2295568,
      "z": -0.3901441
    },
    {
      "x": -3.44447136,
      "y": 0.2531432,
      "z": -0.370552778
    },
    {
      "x": -3.27453518,
      "y": 0.3125509,
      "z": -0.343582153
    },
    {
      "x": -2.98787451,
      "y": 0.283053041,
      "z": -0.296661615
    },
    {
      "x": -2.68454361,
      "y": 0.305722356,
      "z": -0.236760139
    },
    {
      "x": -2.492372,
      "y": 0.352026343,
      "z": -0.188422441
    },
    {
      "x": -2.31179857,
      "y": 0.421128273,
      "z": -0.06511903
    },
    {
      "x": -2.187251,
      "y": 0.462013364,
      "z": 0.07503319
    },
    {
      "x": -2.12843132,
      "y": 0.353197455,
      "z": 0.158713818
    },
    {
      "x": -2.09138155,
      "y": 0.210999131,
      "z": 0.187746525
    },
    {
      "x": -2.05120945,
      "y": 0.241211057,
      "z": 0.205439568
    },
    {
      "x": -2.00807953,
      "y": 0.234394312,
      "z": 0.223389149
    },
    {
      "x": -1.95842028,
      "y": 0.250439644,
      "z": 0.235488415
    },
    {
      "x": -1.768156,
      "y": 0.33326304,
      "z": 0.286969423
    },
    {
      "x": -1.36560726,
      "y": 0.2513522,
      "z": 0.3990109
    },
    {
      "x": -1.20237207,
      "y": 0.221362948,
      "z": 0.46526432
    },
    {
      "x": -1.1936965,
      "y": 0.229103923,
      "z": 0.46435523
    },
    {
      "x": -1.16580868,
      "y": 0.2551608,
      "z": 0.488834143
    },
    {
      "x": -1.154778,
      "y": 0.248864532,
      "z": 0.491673946
    },
    {
      "x": -1.11722422,
      "y": 0.300149441,
      "z": 0.5501542
    },
    {
      "x": -0.7535105,
      "y": 0.395499349,
      "z": 0.7656536
    },
    {
      "x": -0.008865356,
      "y": 0.407317638,
      "z": 0.9555745
    },
    {
      "x": 0.439863682,
      "y": 0.444275618,
      "z": 0.5823288
    },
    {
      "x": 0.39461422,
      "y": 0.305803061,
      "z": 0.257944822
    },
    {
      "x": 0.367679119,
      "y": 0.2163055,
      "z": 0.132496357
    },
    {
      "x": 0.410593033,
      "y": 0.22180891,
      "z": 0.143677235
    },
    {
      "x": 0.437273979,
      "y": 0.2144655,
      "z": 0.138070583
    },
    {
      "x": 0.4850216,
      "y": 0.2421552,
      "z": 0.119210958
    },
    {
      "x": 0.5388627,
      "y": 0.253820181,
      "z": 0.103256464
    },
    {
      "x": 0.6338196,
      "y": 0.2762897,
      "z": 0.1310327
    },
    {
      "x": 0.704988,
      "y": 0.275562525,
      "z": 0.08736801
    },
    {
      "x": 0.750713348,
      "y": 0.295747519,
      "z": 0.0258367062
    },
    {
      "x": 0.7736721,
      "y": 0.256441,
      "z": -0.04381752
    },
    {
      "x": 0.7033105,
      "y": 0.212644577,
      "z": -0.121576786
    },
    {
      "x": 0.6812973,
      "y": 0.2184999,
      "z": -0.118227243
    },
    {
      "x": 0.6495333,
      "y": 0.222185731,
      "z": -0.130175114
    },
    {
      "x": 0.618810654,
      "y": 0.2310437,
      "z": -0.144733429
    },
    {
      "x": 0.572615147,
      "y": 0.237244487,
      "z": -0.16037631
    },
    {
      "x": 0.466676235,
      "y": 0.245621681,
      "z": -0.202903509
    },
    {
      "x": 0.275429249,
      "y": 0.2419622,
      "z": -0.254754066
    },
    {
      "x": -0.0204501152,
      "y": 0.250594616,
      "z": -0.3168509
    },
    {
      "x": -0.326435566,
      "y": 0.3148191,
      "z": -0.357899666
    },
    {
      "x": -0.5313158,
      "y": 0.270048857,
      "z": -0.383055925
    },
    {
      "x": -0.6365204,
      "y": 0.20528686,
      "z": -0.441663027
    },
    {
      "x": -0.6441479,
      "y": 0.215786457,
      "z": -0.4172294
    },
    {
      "x": -0.6697178,
      "y": 0.221356153,
      "z": -0.424013138
    },
    {
      "x": -0.6950097,
      "y": 0.224155545,
      "z": -0.423135281
    },
    {
      "x": -0.7254205,
      "y": 0.228662252,
      "z": -0.419149637
    },
    {
      "x": -0.790797234,
      "y": 0.233193517,
      "z": -0.410112858
    },
    {
      "x": -0.9230404,
      "y": 0.2412703,
      "z": -0.3891847
    },
    {
      "x": -1.12325048,
      "y": 0.243122339,
      "z": -0.349012375
    },
    {
      "x": -1.37508726,
      "y": 0.2422489,
      "z": -0.31444025
    },
    {
      "x": -1.66665792,
      "y": 0.2817613,
      "z": -0.297384739
    },
    {
      "x": -1.87510824,
      "y": 0.328362942,
      "z": -0.291691542
    },
    {
      "x": -2.03854561,
      "y": 0.2498486,
      "z": -0.309027672
    },
    {
      "x": -2.09024954,
      "y": 0.2113105,
      "z": -0.333070755
    },
    {
      "x": -2.09451818,
      "y": 0.2230761,
      "z": -0.3324697
    },
    {
      "x": -2.12011147,
      "y": 0.228845239,
      "z": -0.330402136
    },
    {
      "x": -2.13841152,
      "y": 0.231225967,
      "z": -0.3273158
    },
    {
      "x": -2.15451717,
      "y": 0.235408783,
      "z": -0.327713
    }
  ],
  "UserNonDominantFootPositions": [
    {
      "x": -3.73871613,
      "y": 0.206887841,
      "z": -0.589777946
    },
    {
      "x": -3.72241688,
      "y": 0.215109944,
      "z": -0.5632398
    },
    {
      "x": -3.73329926,
      "y": 0.228822947,
      "z": -0.6082754
    },
    {
      "x": -3.68324566,
      "y": 0.235471964,
      "z": -0.6589103
    },
    {
      "x": -3.618414,
      "y": 0.26634717,
      "z": -0.6773007
    },
    {
      "x": -3.594674,
      "y": 0.312452435,
      "z": -0.624366045
    },
    {
      "x": -3.45303249,
      "y": 0.275617242,
      "z": -0.5910685
    },
    {
      "x": -3.271968,
      "y": 0.2302289,
      "z": -0.557763338
    },
    {
      "x": -3.11405,
      "y": 0.235700369,
      "z": -0.5277605
    },
    {
      "x": -3.02894926,
      "y": 0.244569778,
      "z": -0.5218265
    },
    {
      "x": -3.05013227,
      "y": 0.229620337,
      "z": -0.532806158
    },
    {
      "x": -3.04311323,
      "y": 0.22029233,
      "z": -0.526776552
    },
    {
      "x": -3.056758,
      "y": 0.213830471,
      "z": -0.5422673
    },
    {
      "x": -3.06043816,
      "y": 0.223361135,
      "z": -0.5453894
    },
    {
      "x": -3.039494,
      "y": 0.223524928,
      "z": -0.534026146
    },
    {
      "x": -3.022727,
      "y": 0.210704327,
      "z": -0.53002
    },
    {
      "x": -2.99950123,
      "y": 0.248961568,
      "z": -0.5262265
    },
    {
      "x": -2.803442,
      "y": 0.3212223,
      "z": -0.4278376
    },
    {
      "x": -2.467671,
      "y": 0.18403697,
      "z": -0.287458181
    },
    {
      "x": -2.45525074,
      "y": 0.2117095,
      "z": -0.260592937
    },
    {
      "x": -2.45605659,
      "y": 0.3056581,
      "z": -0.2822039
    },
    {
      "x": -2.34783077,
      "y": 0.3210168,
      "z": -0.173297644
    },
    {
      "x": -2.11759043,
      "y": 0.273638248,
      "z": -0.0111718178
    },
    {
      "x": -2.04098988,
      "y": 0.251580477,
      "z": 0.0404951572
    },
    {
      "x": -2.01099968,
      "y": 0.252586842,
      "z": 0.0493586063
    },
    {
      "x": -1.93820572,
      "y": 0.298053384,
      "z": 0.06252146
    },
    {
      "x": -1.69976044,
      "y": 0.353520632,
      "z": 0.129901171
    },
    {
      "x": -1.39424467,
      "y": 0.3539039,
      "z": 0.21995759
    },
    {
      "x": -0.9714718,
      "y": 0.288169026,
      "z": 0.340111256
    },
    {
      "x": -0.431108475,
      "y": 0.2557732,
      "z": 0.477082253
    },
    {
      "x": -0.209016323,
      "y": 0.205234647,
      "z": 0.5491009
    },
    {
      "x": -0.162455559,
      "y": 0.188241959,
      "z": 0.618097067
    },
    {
      "x": -0.172020435,
      "y": 0.209710479,
      "z": 0.5537882
    },
    {
      "x": -0.150656223,
      "y": 0.278529525,
      "z": 0.3407719
    },
    {
      "x": -0.0127353668,
      "y": 0.464992166,
      "z": -0.0161261559
    },
    {
      "x": 0.515496731,
      "y": 0.322073817,
      "z": -0.152124166
    },
    {
      "x": 1.50732017,
      "y": 0.231281042,
      "z": -0.0950865746
    },
    {
      "x": 1.22319555,
      "y": 0.312713146,
      "z": 0.02755785
    },
    {
      "x": 1.12954831,
      "y": 0.164029,
      "z": -0.0726335049
    },
    {
      "x": 1.06421232,
      "y": 0.150781035,
      "z": 0.0117211342
    },
    {
      "x": 0.9748676,
      "y": 0.1258583,
      "z": 0.08681774
    },
    {
      "x": 0.859534264,
      "y": 0.08809829,
      "z": 0.148974657
    },
    {
      "x": 0.7461386,
      "y": 0.0431790352,
      "z": 0.198764563
    },
    {
      "x": 0.633101,
      "y": 0.0232871771,
      "z": 0.164510489
    },
    {
      "x": 0.8816552,
      "y": 0.238330126,
      "z": -0.302806377
    },
    {
      "x": 0.553745747,
      "y": 0.291890144,
      "z": -0.449090242
    },
    {
      "x": 0.270902634,
      "y": 0.328638434,
      "z": -0.5417805
    },
    {
      "x": 0.077703476,
      "y": 0.232854486,
      "z": -0.5574744
    },
    {
      "x": 0.0717334747,
      "y": 0.205653429,
      "z": -0.5531881
    },
    {
      "x": 0.0504608154,
      "y": 0.205872774,
      "z": -0.559227
    },
    {
      "x": 0.0334205627,
      "y": 0.212940335,
      "z": -0.5711515
    },
    {
      "x": 0.008256912,
      "y": 0.21481812,
      "z": -0.5717783
    },
    {
      "x": -0.024189949,
      "y": 0.22004652,
      "z": -0.5782542
    },
    {
      "x": -0.08937454,
      "y": 0.228356242,
      "z": -0.590139866
    },
    {
      "x": -0.284202576,
      "y": 0.237374544,
      "z": -0.613342047
    },
    {
      "x": -0.601721764,
      "y": 0.261121035,
      "z": -0.6340275
    },
    {
      "x": -0.9403777,
      "y": 0.333399653,
      "z": -0.6326153
    },
    {
      "x": -1.18439484,
      "y": 0.281757,
      "z": -0.62806344
    },
    {
      "x": -1.37282324,
      "y": 0.224395871,
      "z": -0.5657015
    },
    {
      "x": -1.38249779,
      "y": 0.205242872,
      "z": -0.5623231
    },
    {
      "x": -1.40017843,
      "y": 0.2096008,
      "z": -0.567234755
    },
    {
      "x": -1.41874981,
      "y": 0.2134918,
      "z": -0.573787451
    },
    {
      "x": -1.43116236,
      "y": 0.217801213,
      "z": -0.5757611
    },
    {
      "x": -1.44486475,
      "y": 0.220627785,
      "z": -0.575206757
    },
    {
      "x": -1.47506285,
      "y": 0.225499749,
      "z": -0.5781059
    },
    {
      "x": -1.53699017,
      "y": 0.23756361,
      "z": -0.582587
    },
    {
      "x": -1.74891043,
      "y": 0.242975712,
      "z": -0.581692
    },
    {
      "x": -2.0353322,
      "y": 0.258535147,
      "z": -0.5786681
    },
    {
      "x": -2.33529234,
      "y": 0.3133551,
      "z": -0.5866146
    },
    {
      "x": -2.55376768,
      "y": 0.29958427,
      "z": -0.6037147
    }
  ],
  "UserHipPositions": [
    {
      "x": -3.51520729,
      "y": 1.04016948,
      "z": -0.5124824
    },
    {
      "x": -3.489172,
      "y": 1.04251182,
      "z": -0.483276129
    },
    {
      "x": -3.46202564,
      "y": 1.04692042,
      "z": -0.464437962
    },
    {
      "x": -3.449047,
      "y": 1.04873919,
      "z": -0.458557844
    },
    {
      "x": -3.401617,
      "y": 1.05542815,
      "z": -0.414089918
    },
    {
      "x": -3.389368,
      "y": 1.053133,
      "z": -0.422051668
    },
    {
      "x": -3.34888268,
      "y": 1.04873443,
      "z": -0.398048162
    },
    {
      "x": -3.31473064,
      "y": 1.05075133,
      "z": -0.3878374
    },
    {
      "x": -3.28004265,
      "y": 1.04487836,
      "z": -0.381274223
    },
    {
      "x": -3.23765373,
      "y": 1.04124868,
      "z": -0.379773617
    },
    {
      "x": -3.17109871,
      "y": 1.02980042,
      "z": -0.372479677
    },
    {
      "x": -3.08488274,
      "y": 1.0287199,
      "z": -0.377559423
    },
    {
      "x": -3.01118279,
      "y": 1.034698,
      "z": -0.369113445
    },
    {
      "x": -2.93788528,
      "y": 1.07398653,
      "z": -0.3507886
    },
    {
      "x": -2.87948132,
      "y": 1.02617288,
      "z": -0.338567257
    },
    {
      "x": -2.77974415,
      "y": 0.9906517,
      "z": -0.290136576
    },
    {
      "x": -2.63847923,
      "y": 1.03457034,
      "z": -0.2436707
    },
    {
      "x": -2.47244787,
      "y": 1.09022284,
      "z": -0.162063122
    },
    {
      "x": -2.356598,
      "y": 1.0384742,
      "z": -0.1123817
    },
    {
      "x": -2.19391966,
      "y": 0.9806235,
      "z": -0.0198585987
    },
    {
      "x": -2.070722,
      "y": 1.013197,
      "z": 0.06242156
    },
    {
      "x": -1.92078733,
      "y": 1.04161286,
      "z": 0.123056889
    },
    {
      "x": -1.79044437,
      "y": 1.05086756,
      "z": 0.154403687
    },
    {
      "x": -1.6947422,
      "y": 1.01930857,
      "z": 0.2164948
    },
    {
      "x": -1.56215429,
      "y": 0.9682006,
      "z": 0.26878047
    },
    {
      "x": -1.35166168,
      "y": 0.9310035,
      "z": 0.2974782
    },
    {
      "x": -1.228528,
      "y": 0.996068656,
      "z": 0.394312859
    },
    {
      "x": -1.06012821,
      "y": 0.984074831,
      "z": 0.42002058
    },
    {
      "x": -0.886710167,
      "y": 0.9808536,
      "z": 0.4670012
    },
    {
      "x": -0.6370659,
      "y": 1.00716257,
      "z": 0.4974723
    },
    {
      "x": -0.4095068,
      "y": 1.00899673,
      "z": 0.497846127
    },
    {
      "x": -0.233361721,
      "y": 0.924301744,
      "z": 0.454308271
    },
    {
      "x": -0.0544805527,
      "y": 0.9948463,
      "z": 0.3684125
    },
    {
      "x": 0.12061739,
      "y": 1.03304935,
      "z": 0.29877162
    },
    {
      "x": 0.300207138,
      "y": 0.988718,
      "z": 0.263167143
    },
    {
      "x": 0.420278549,
      "y": 0.938346565,
      "z": 0.253822327
    },
    {
      "x": 0.5760193,
      "y": 0.9200683,
      "z": 0.165560961
    },
    {
      "x": 0.657341957,
      "y": 0.9131147,
      "z": 0.197611332
    },
    {
      "x": 0.773393154,
      "y": 0.899031758,
      "z": 0.155774117
    },
    {
      "x": 0.807765961,
      "y": 0.8979912,
      "z": 0.121760368
    },
    {
      "x": 0.8401642,
      "y": 0.9099479,
      "z": 0.08426309
    },
    {
      "x": 0.825116158,
      "y": 0.9425539,
      "z": 0.03786397
    },
    {
      "x": 0.7786417,
      "y": 0.9742095,
      "z": -0.01815772
    },
    {
      "x": 0.7099652,
      "y": 0.999834538,
      "z": -0.07390571
    },
    {
      "x": 0.6189952,
      "y": 1.02238047,
      "z": -0.129035234
    },
    {
      "x": 0.533694267,
      "y": 1.03026438,
      "z": -0.177826881
    },
    {
      "x": 0.444468021,
      "y": 1.02958941,
      "z": -0.231568575
    },
    {
      "x": 0.32646513,
      "y": 1.0003891,
      "z": -0.300905466
    },
    {
      "x": 0.197548389,
      "y": 1.02546144,
      "z": -0.332312584
    },
    {
      "x": 0.08507776,
      "y": 1.05646574,
      "z": -0.3656094
    },
    {
      "x": -0.0265407562,
      "y": 1.0659337,
      "z": -0.395328045
    },
    {
      "x": -0.124743462,
      "y": 1.05281544,
      "z": -0.401022434
    },
    {
      "x": -0.258087635,
      "y": 1.02936053,
      "z": -0.401282549
    },
    {
      "x": -0.412709236,
      "y": 1.02313185,
      "z": -0.3942678
    },
    {
      "x": -0.5467386,
      "y": 1.05767107,
      "z": -0.407403946
    },
    {
      "x": -0.6595769,
      "y": 1.064541,
      "z": -0.417062759
    },
    {
      "x": -0.780207157,
      "y": 1.04977512,
      "z": -0.420120716
    },
    {
      "x": -0.9162164,
      "y": 1.01614285,
      "z": -0.4286585
    },
    {
      "x": -1.06460285,
      "y": 0.9910072,
      "z": -0.440274239
    },
    {
      "x": -1.19475174,
      "y": 1.02578259,
      "z": -0.450002432
    },
    {
      "x": -1.29425192,
      "y": 1.05737948,
      "z": -0.439927816
    },
    {
      "x": -1.3929944,
      "y": 1.07333744,
      "z": -0.4253981
    },
    {
      "x": -1.492909,
      "y": 1.073873,
      "z": -0.410043478
    },
    {
      "x": -1.588521,
      "y": 1.06099343,
      "z": -0.395756
    },
    {
      "x": -1.71876192,
      "y": 1.03600323,
      "z": -0.374982834
    },
    {
      "x": -1.86282444,
      "y": 1.04122949,
      "z": -0.365964651
    },
    {
      "x": -1.96846771,
      "y": 1.07156539,
      "z": -0.3698454
    },
    {
      "x": -2.06289577,
      "y": 1.06610978,
      "z": -0.3763287
    },
    {
      "x": -2.15073013,
      "y": 1.05957413,
      "z": -0.38539362
    },
    {
      "x": -2.24907112,
      "y": 1.04428709,
      "z": -0.399976969
    }
  ],
  "OpponentHipPositions": [
    {
      "x": 4.330979,
      "y": 0.941835344,
      "z": 0.437265873
    },
    {
      "x": 4.326656,
      "y": 0.945473731,
      "z": 0.433184147
    },
    {
      "x": 4.325237,
      "y": 0.9480103,
      "z": 0.427865028
    },
    {
      "x": 4.322321,
      "y": 0.9525276,
      "z": 0.423807859
    },
    {
      "x": 4.31803751,
      "y": 0.9587987,
      "z": 0.416404724
    },
    {
      "x": 4.31182051,
      "y": 0.962212443,
      "z": 0.4082265
    },
    {
      "x": 4.29553556,
      "y": 0.963065445,
      "z": 0.4024074
    },
    {
      "x": 4.27214527,
      "y": 0.965751946,
      "z": 0.402106285
    },
    {
      "x": 4.254407,
      "y": 0.9673124,
      "z": 0.405941248
    },
    {
      "x": 4.24521,
      "y": 0.9677381,
      "z": 0.410791159
    },
    {
      "x": 4.23963642,
      "y": 0.9634356,
      "z": 0.407953978
    },
    {
      "x": 4.22640753,
      "y": 0.96409446,
      "z": 0.402929783
    },
    {
      "x": 4.19806671,
      "y": 0.9601354,
      "z": 0.400016069
    },
    {
      "x": 4.142083,
      "y": 0.9380635,
      "z": 0.401354074
    },
    {
      "x": 4.064799,
      "y": 0.913303256,
      "z": 0.4158442
    },
    {
      "x": 3.982781,
      "y": 0.9273279,
      "z": 0.423721075
    },
    {
      "x": 3.90266037,
      "y": 0.988108,
      "z": 0.423537731
    },
    {
      "x": 3.82165146,
      "y": 1.03856,
      "z": 0.451914072
    },
    {
      "x": 3.75997686,
      "y": 0.965201557,
      "z": 0.476241827
    },
    {
      "x": 3.66745472,
      "y": 0.8783101,
      "z": 0.50001
    },
    {
      "x": 3.46608353,
      "y": 0.8597636,
      "z": 0.57545495
    },
    {
      "x": 3.27566075,
      "y": 0.8760487,
      "z": 0.651849031
    },
    {
      "x": 3.10968018,
      "y": 0.9453019,
      "z": 0.6877265
    },
    {
      "x": 2.96003985,
      "y": 0.9378632,
      "z": 0.7353008
    },
    {
      "x": 2.784205,
      "y": 0.8683858,
      "z": 0.8123083
    },
    {
      "x": 2.580782,
      "y": 0.825567245,
      "z": 0.9129081
    },
    {
      "x": 2.5343852,
      "y": 0.7550477,
      "z": 1.0002377
    },
    {
      "x": 2.55267549,
      "y": 0.7120353,
      "z": 1.06676865
    },
    {
      "x": 2.41137481,
      "y": 0.7601981,
      "z": 0.9144361
    },
    {
      "x": 2.36483884,
      "y": 0.796552539,
      "z": 0.991471052
    },
    {
      "x": 2.34917855,
      "y": 0.909595132,
      "z": 1.01456118
    },
    {
      "x": 2.38340974,
      "y": 0.9763673,
      "z": 0.9988272
    },
    {
      "x": 2.416122,
      "y": 0.9434795,
      "z": 1.03809381
    },
    {
      "x": 2.45929027,
      "y": 0.866273761,
      "z": 0.917732
    },
    {
      "x": 2.58920765,
      "y": 0.9443041,
      "z": 0.8140197
    },
    {
      "x": 2.74149346,
      "y": 1.06773114,
      "z": 0.7482712
    },
    {
      "x": 2.85366488,
      "y": 1.01117349,
      "z": 0.6895225
    },
    {
      "x": 2.978935,
      "y": 0.929155231,
      "z": 0.6159985
    },
    {
      "x": 3.14174414,
      "y": 1.004074,
      "z": 0.485115528
    },
    {
      "x": 3.252101,
      "y": 0.980386257,
      "z": 0.438918829
    },
    {
      "x": 3.44995117,
      "y": 0.9294402,
      "z": 0.44161725
    },
    {
      "x": 3.64606619,
      "y": 0.9409972,
      "z": 0.420455217
    },
    {
      "x": 3.88712358,
      "y": 1.02323222,
      "z": 0.388725758
    },
    {
      "x": 4.12695169,
      "y": 1.03328633,
      "z": 0.416332
    },
    {
      "x": 4.32119226,
      "y": 0.928542,
      "z": 0.481392622
    },
    {
      "x": 4.44511032,
      "y": 0.9410918,
      "z": 0.541049957
    },
    {
      "x": 4.57829,
      "y": 0.965462565,
      "z": 0.6065557
    },
    {
      "x": 4.7080946,
      "y": 1.00033092,
      "z": 0.677126169
    },
    {
      "x": 4.859182,
      "y": 1.0054462,
      "z": 0.7344501
    },
    {
      "x": 5.017562,
      "y": 0.9581952,
      "z": 0.7894671
    },
    {
      "x": 5.109005,
      "y": 0.9916755,
      "z": 0.8564527
    },
    {
      "x": 5.220686,
      "y": 1.03468955,
      "z": 0.9034951
    },
    {
      "x": 5.301598,
      "y": 1.039127,
      "z": 0.968786
    },
    {
      "x": 5.38105631,
      "y": 1.02528214,
      "z": 1.03841019
    },
    {
      "x": 5.484215,
      "y": 1.00419664,
      "z": 1.13360643
    },
    {
      "x": 5.57879829,
      "y": 1.00137138,
      "z": 1.23619342
    },
    {
      "x": 5.67452526,
      "y": 1.01775873,
      "z": 1.29937673
    },
    {
      "x": 5.728812,
      "y": 1.01241481,
      "z": 1.36724257
    },
    {
      "x": 5.806343,
      "y": 1.0039171,
      "z": 1.423423
    },
    {
      "x": 5.89573145,
      "y": 0.9870592,
      "z": 1.4920156
    },
    {
      "x": 6.01745653,
      "y": 0.9843574,
      "z": 1.56821561
    },
    {
      "x": 6.13744354,
      "y": 0.9855259,
      "z": 1.62991643
    },
    {
      "x": 6.227668,
      "y": 1.00912011,
      "z": 1.68945813
    },
    {
      "x": 6.31991863,
      "y": 1.02107835,
      "z": 1.72918963
    },
    {
      "x": 6.40748167,
      "y": 1.01264346,
      "z": 1.79172254
    },
    {
      "x": 6.503448,
      "y": 0.998036444,
      "z": 1.86772227
    },
    {
      "x": 6.63460636,
      "y": 1.01808333,
      "z": 1.9691155
    },
    {
      "x": 6.76829433,
      "y": 1.0341804,
      "z": 2.075271
    },
    {
      "x": 6.86893225,
      "y": 1.03923523,
      "z": 2.17526555
    },
    {
      "x": 6.97454071,
      "y": 1.03727651,
      "z": 2.27333713
    }
  ]
}